sprit/__init__.py
sprit/sprit_calibration.py
sprit/sprit_cli.py
sprit/sprit_hvsr.py
sprit/sprit_jupyter_UI.py
sprit/sprit_plot.py
sprit/sprit_streamlit_ui.py
sprit/sprit_utils.py
sprit/resources/TrominoSingleGeophoneresponsespectrum.png
sprit/resources/defaults.json
sprit/resources/html_report_template.html
sprit/resources/parameters.csv
sprit/resources/rs3dv5plus_metadata.inv
sprit/resources/hvsrscripts/Readme.md
sprit/resources/hvsrscripts/hvsr_v1-3.sh
sprit/resources/hvsrscripts/old_versions/hvsr_v1-0_2024-07-31.sh
sprit/resources/hvsrscripts/old_versions/hvsr_v1-1_unix.sh
sprit/resources/hvsrscripts/old_versions/hvsr_v1-1_win.sh
sprit/resources/hvsrscripts/old_versions/hvsr_v1-2.sh
sprit/resources/icon/SpRITLogo.png
sprit/resources/icon/SpRITLogo.svg
sprit/resources/icon/SpRITLogo_WhiteBG.png
sprit/resources/icon/sprit_icon__waves_alpha.ico
sprit/resources/icon/sprit_icon_thickly.xcf
sprit/resources/icon/sprit_waves_old.xcf
sprit/resources/icon/sprit_waves_old_icon.png
sprit/resources/sample_data/Batch_SampleData.csv
sprit/resources/sample_data/SampleHVSRSite01.MSEED
sprit/resources/sample_data/SampleHVSRSite01.hvsr
sprit/resources/sample_data/SampleHVSRSite01_v343.json
sprit/resources/sample_data/SampleHVSRSite02.MSEED
sprit/resources/sample_data/SampleHVSRSite02.hvsr
sprit/resources/sample_data/SampleHVSRSite03.MSEED
sprit/resources/sample_data/SampleHVSRSite04.MSEED
sprit/resources/sample_data/SampleHVSRSite05.MSEED
sprit/resources/sample_data/SampleHVSRSite06.MSEED
sprit/resources/sample_data/SampleHVSRSite07.MSEED
sprit/resources/sample_data/SampleHVSRSite08.MSEED
sprit/resources/sample_data/SampleHVSRSite09.MSEED
sprit/resources/sample_data/SampleHVSRSite10.MSEED
sprit/resources/settings/gui_theme.json
sprit/resources/settings/instrument_settings.inst
sprit/resources/settings/processing_settings.proc
sprit/resources/themes/LICENSE
sprit/resources/themes/README.md
sprit/resources/themes/forest-dark.tcl
sprit/resources/themes/forest-light.tcl
sprit-3.5.dist-info/licenses/LICENSE
sprit-3.5.dist-info/METADATA
sprit-3.5.dist-info/WHEEL
sprit-3.5.dist-info/entry_points.txt
sprit-3.5.dist-info/top_level.txt
sprit-3.5.dist-info/RECORD
