Metadata-Version: 2.4
Name: sprit
Version: 3.5
Summary: A package for processing and analyzing HVSR (Horizontal to Vertical Spectral Ratio) data
Author: Riley Balikian
Author-email: balikian@illinois.edu
License: MIT License
Project-URL: Homepage, https://github.com/RJbalikian/SPRIT-HVSR
Project-URL: SpRIT Web App, https://sprithvsr.streamlit.app
Project-URL: ReadtheDocs API Docs, https://sprit.readthedocs.io/en/latest/sprit.html
Project-URL: SpRIT App (streamlit) Docs, https://github.com/RJbalikian/sprit-streamlit/wiki
Project-URL: Github Pages API Docs, https://rjbalikian.github.io/SPRIT-HVSR/main.html
Project-URL: Tutorials & Wiki, https://github.com/RJbalikian/SPRIT-HVSR/wiki
Keywords: HVSR,seismic,horizontal to vertical spectral ratio,obspy,geology,geophysics,geotechnical
Classifier: Programming Language :: Python :: 3
Classifier: Intended Audience :: Science/Research
Classifier: License :: OSI Approved :: MIT License
Classifier: Operating System :: OS Independent
Requires-Python: >=3.9
License-File: LICENSE
Requires-Dist: anywidget
Requires-Dist: ipython
Requires-Dist: ipywidgets
Requires-Dist: kaleido
Requires-Dist: matplotlib
Requires-Dist: nbformat
Requires-Dist: numpy
Requires-Dist: obspy
Requires-Dist: pandas
Requires-Dist: plotly
Requires-Dist: pyproj
Requires-Dist: PyQt5-sip
Requires-Dist: scipy
Requires-Dist: shapely
Requires-Dist: streamlit
Requires-Dist: xhtml2pdf
Dynamic: author-email
Dynamic: description
Dynamic: description-content-type
Dynamic: license-file
Dynamic: requires-python
